{
    "names": {
        "la": "Ignatius",
        "en": "Ignatius"
    },
    "translations": {
        "la": [
            "Ignatius"
        ],
        "en": [
            "Ignatius"
        ],
        "pl": [
            "Ignacy"
        ],
        "es": [
            "Ignacio"
        ]
    },
    "links": {
        "records/patrons/ignatius/loy": {
            "es": "Ignacio de Loyola",
            "la": "Ignatius de Loyola",
            "en": "Ignatius of Loyola",
            "pl": "Ignacy Loyola"
        }
    }
}