{
    "names": {
        "en": "John"
    },
    "translations": {
        "it": [
            "Giovanni"
        ],
        "en": [
            "John"
        ],
        "la": [
            "Ioannes"
        ],
        "pl": [
            "Jan"
        ],
        "fr": [
            "Jean"
        ]
    },
    "links": {
        "records/patrons/ioannes/23p": {
            "it": "Giovanni XXIII",
            "en": "John XXIII",
            "la": "Ioannes Pp. XXIII",
            "pl": "Jan XXIII"
        },
        "records/patrons/ioannes/bap": {
            "he": "יוֹחָנָן",
            "en": "John the Baptist",
            "la": "Ioannes Baptista",
            "pl": "Jan Chrzciciel"
        },
        "records/patrons/ioannes/chr": {
            "la": "Ioannes Chrysostomus",
            "en": "John Chrysostom",
            "pl": "Jan Chryzostom"
        },
        "records/patrons/ioannes/eva": {
            "la": "Ioannes Evangelista",
            "en": "John the Evangelist",
            "pl": "Jan Ewangelista"
        },
        "records/patrons/ioannes/p2p": {
            "pl": "Jan Paweł II",
            "en": "John Paul II",
            "la": "Ioannes Paulus Pp. II"
        },
        "records/patrons/ioannes/via": {
            "fr": "Jean-Marie Vianney",
            "en": "John Mary Vianney",
            "la": "Ioannes Maria Vianney",
            "pl": "Jan Maria Vianney"
        }
    }
}