{
  "names": {
    "it": [
      "Giovanni XXIII",
      "Angelo Giuseppe Roncalli"
    ],
    "en": [
      "John XXIII",
      "Angelo Giuseppe Roncalli"
    ],
    "la": [
      "Ioannes Pp. XXIII",
      "Ioannes XXIII",
      "Angelo Giuseppe Roncalli"
    ],
    "pl": [
      "Jan XXIII",
      "Angelo Giuseppe Roncalli"
    ]
  },

  "epithets": [
    {
      "en": "the Twenty-Third",
      "la": "Vigesimus Tertius",
      "pl": "Dwudziesty Trzeci"
    }
  ],

  "born": ["1881-11-25"],
  "died": ["1963-06-03"],

  "beatified": {
    "type": "ceremonially",
    "date": "2000-09-03"
  },
  "canonized": {
    "type": "ceremonially",
    "date": "2014-04-27"
  },

  "also-in-martyrology": ["06-03"],

  "forenames": ["ioannes"],
  "categories": ["vir", "papa"],

  "data-links": {
    "popes": ["1:#261"]
  }
}
