{
  "names": {
    "es": [
      "Juan de Ribera"
    ],
    "en": [
      "John de Ribera"
    ],
    "la": [
      "Ioannes de Ribera"
    ],
    "pl": [
      "Jan de Ribera"
    ]
  },

  "surnames": [
    {
      "es": "de Ribera"
    }
  ],

  "born": ["1532-12-27"],
  "died": ["1611-01-06"],

  "beatified": {
    "type": "ceremonially",
    "date": "1796-09-18"
  },
  "canonized": {
    "type": "ceremonially",
    "date": "1960-06-12"
  },

  "also-in-martyrology": ["01-06"],

  "forenames": ["ioannes"],
  "categories": ["vir", "episcopus", "rex"]
}
