{
    "names": {
        "pl": "prorok"
    },
    "translations": {
        "la": [
            "propheta"
        ],
        "en": [
            "prophet"
        ],
        "pl": [
            "prorok"
        ]
    },
    "links": {
        "records/patrons/ezechiel/pro": {
            "he": "יְחֶזְקֵאל",
            "en": "Ezekiel",
            "la": "Ezechiel",
            "pl": "Ezechiel"
        },
        "records/patrons/ioannes/bap": {
            "he": "יוֹחָנָן",
            "en": "John the Baptist",
            "la": "Ioannes Baptista",
            "pl": "Jan Chrzciciel"
        },
        "records/patrons/isaias/pro": {
            "he": "יְשַׁעְיָהוּ",
            "en": "Isaiah",
            "la": "Isaias",
            "pl": "Izajasz"
        },
        "records/patrons/malachias/pro": {
            "la": "Malachias Propheta",
            "en": "Malachi the Prophet",
            "pl": "Malachiasz Prorok"
        }
    }
}